opsys_camera_controller/__init__.py
opsys_camera_controller/camera_abstract.py
opsys_camera_controller/camera_controller.py
opsys_camera_controller/configs.py
opsys_camera_controller/ids/__init__.py
opsys_camera_controller/ids/ids_camera.py
opsys_camera_controller/ids/ids_peak_camera.py
opsys_camera_controller/ids/ueye_api_64.dll
opsys_camera_controller/ids/ids_peak/__init__.py
opsys_camera_controller/ids/ids_peak/_ids_peak_ipl_python_extension.pyd
opsys_camera_controller/ids/ids_peak/_ids_peak_python_interface.pyd
opsys_camera_controller/ids/ids_peak/ids_peak.py
opsys_camera_controller/ids/ids_peak/ids_peak_ipl_extension.py
opsys_camera_controller/ids/ids_peak_ipl/__init__.py
opsys_camera_controller/ids/ids_peak_ipl/_peak_ipl_python_interface.pyd
opsys_camera_controller/ids/ids_peak_ipl/ids_peak_ipl.py
opsys_camera_controller/vimba/__init__.py
opsys_camera_controller/vimba/allied_camera.py
opsys_camera_controller/vimba/camera.py
opsys_camera_controller/vimba/error.py
opsys_camera_controller/vimba/feature.py
opsys_camera_controller/vimba/frame.py
opsys_camera_controller/vimba/interface.py
opsys_camera_controller/vimba/shared.py
opsys_camera_controller/vimba/vimba.py
opsys_camera_controller/vimba/c_binding/__init__.py
opsys_camera_controller/vimba/c_binding/vimba_c.py
opsys_camera_controller/vimba/c_binding/vimba_common.py
opsys_camera_controller/vimba/c_binding/vimba_image_transform.py
opsys_camera_controller/vimba/util/__init__.py
opsys_camera_controller/vimba/util/context_decorator.py
opsys_camera_controller/vimba/util/log.py
opsys_camera_controller/vimba/util/runtime_type_check.py
opsys_camera_controller/vimba/util/scoped_log.py
opsys_camera_controller/vimba/util/tracer.py
opsys_camera_controller-0.0.7.dist-info/LICENSE
opsys_camera_controller-0.0.7.dist-info/METADATA
opsys_camera_controller-0.0.7.dist-info/WHEEL
opsys_camera_controller-0.0.7.dist-info/top_level.txt
opsys_camera_controller-0.0.7.dist-info/RECORD
