Metadata-Version: 2.1
Name: opsys-camera-controller
Version: 0.0.7
Summary: python package for camera devices control
Home-page: https://bitbucket.org/opsys_tech/opsys-camera-controller/src/master/
Download-URL: https://bitbucket.org/opsys_tech/opsys-camera-controller/src/master/
Author: dmitry.borovensky
Author-email: dmitry.borovensky@opsys-tech.com
License-File: LICENSE
